abc_of_matrix_algebra/__init__.py
abc_of_matrix_algebra/basic_matrix_operations.py
abc_of_matrix_algebra-1.0.dist-info/METADATA
abc_of_matrix_algebra-1.0.dist-info/WHEEL
abc_of_matrix_algebra-1.0.dist-info/top_level.txt
abc_of_matrix_algebra-1.0.dist-info/RECORD
