Metadata-Version: 2.1
Name: abc_of_matrix_algebra
Version: 1.0
Summary: A package for basic matrix algebra operations
Home-page: https://github.com/BrianMeki/matrix_algebra
Author: Brian Meki
Author-email: brian.meki@takealot.com
License: MIT
Classifier: Programming Language :: Python :: 3
Classifier: License :: OSI Approved :: MIT License
